{
	"format_version": "1.8.0",
	"animations": {
		"animation.regigigas.ground_idle": {
			"loop": true,
			"bones": {
				"torso": {
					"rotation": [-2.5, 0, 0]
				},
				"chest": {
					"rotation": [0, 0, 0]
				},
				"shoulder_left": {
					"rotation": [4.99527, -0.21782, 2.4905]
				},
				"arm_left_rotation": {
					"rotation": [-6.1191, 21.69365, 36.32646]
				},
				"arm_left2": {
					"rotation": [0, 42.5, 0]
				},
				"hand_left": {
					"rotation": [0, 15, 0]
				},
				"finger1_left": {
					"rotation": [0, 5, -17.5]
				},
				"finger1_left2": {
					"rotation": [0, 0, 32.5]
				},
				"finger2_left": {
					"rotation": [29.87229, 22.01609, 12.15123]
				},
				"finger2_left2": {
					"rotation": [0, -30, 0]
				},
				"finger3_left": {
					"rotation": [-29.39942, -19.84302, 10.82777]
				},
				"finger3_left2": {
					"rotation": [0, 32.5, 0]
				},
				"shoulder_right": {
					"rotation": [4.99527, 0.21782, -2.4905]
				},
				"arm_right_rotation": {
					"rotation": [-6.1191, -21.69365, -36.32646]
				},
				"arm_right2": {
					"rotation": [0, -42.5, 0]
				},
				"hand_right": {
					"rotation": [0, -15, 0]
				},
				"finger1_right": {
					"rotation": [0, -5, 17.5]
				},
				"finger1_right2": {
					"rotation": [0, 0, -32.5]
				},
				"finger2_right": {
					"rotation": [29.87229, -22.01609, -12.15123]
				},
				"finger2_right2": {
					"rotation": [0, 30, 0]
				},
				"finger3_right": {
					"rotation": [-29.39942, 19.84302, -10.82777]
				},
				"finger3_right2": {
					"rotation": [0, -32.5, 0]
				},
				"leg_left": {
					"rotation": [-7.5, 0, 0]
				},
				"leg_left2": {
					"rotation": [7.44083, -1.29114, 4.8259]
				},
				"foot_left": {
					"rotation": [-2.5, 0, 5]
				},
				"leg_right": {
					"rotation": [-7.5, 0, 0]
				},
				"leg_right2": {
					"rotation": [7.44083, 1.29114, -4.8259]
				},
				"foot_right": {
					"rotation": [-2.5, 0, -5]
				},
				"body": {
					"position": [0, 1, 0]
				},
				"foot_left_pivot": {
					"rotation": [2.5, 0, 0]
				},
				"arm_left": {
					"rotation": [37.5, 0, 0]
				},
				"arm_right": {
					"rotation": [37.5, 0, 0]
				},
				"foot_right_pivot": {
					"rotation": [2.5, 0, 0]
				}
			}
		},
		"animation.regigigas.battle_idle": {
			"loop": true,
			"bones": {
				"torso": {
					"rotation": [-5, 0, 0]
				},
				"chest": {
					"rotation": [2.5, 0, 0]
				},
				"shoulder_left": {
					"rotation": [4.99527, -0.21782, 2.4905]
				},
				"arm_left_rotation": {
					"rotation": [3.25213, 0.0374, 42.53765]
				},
				"arm_left2": {
					"rotation": [0, 35, 0]
				},
				"hand_left": {
					"rotation": [0, 15, 0]
				},
				"finger1_left": {
					"rotation": [0, 5, -17.5]
				},
				"finger1_left2": {
					"rotation": [0, 0, 32.5]
				},
				"finger2_left": {
					"rotation": [29.87229, 22.01609, 12.15123]
				},
				"finger2_left2": {
					"rotation": [0, -30, 0]
				},
				"finger3_left": {
					"rotation": [-29.39942, -19.84302, 10.82777]
				},
				"finger3_left2": {
					"rotation": [0, 32.5, 0]
				},
				"shoulder_right": {
					"rotation": [4.99527, 0.21782, -2.4905]
				},
				"arm_right_rotation": {
					"rotation": [3.25213, -0.0374, -42.53765]
				},
				"arm_right2": {
					"rotation": [0, -35, 0]
				},
				"hand_right": {
					"rotation": [0, -15, 0]
				},
				"finger1_right": {
					"rotation": [0, -5, 17.5]
				},
				"finger1_right2": {
					"rotation": [0, 0, -32.5]
				},
				"finger2_right": {
					"rotation": [29.87229, -22.01609, -12.15123]
				},
				"finger2_right2": {
					"rotation": [0, 30, 0]
				},
				"finger3_right": {
					"rotation": [-29.39942, 19.84302, -10.82777]
				},
				"finger3_right2": {
					"rotation": [0, -32.5, 0]
				},
				"legs": {
					"rotation": [0, -25, 0]
				},
				"leg_left": {
					"rotation": [2.21212, 29.5374, -1.50181],
					"position": [0, 0, 2]
				},
				"leg_left2": {
					"rotation": [12.44083, -1.29114, 4.8259]
				},
				"foot_left": {
					"rotation": [-2.5, 0, 5]
				},
				"leg_right": {
					"rotation": [-21.82326, 19.73356, -6.09788]
				},
				"leg_right2": {
					"rotation": [17.5, 0, 0]
				},
				"foot_right": {
					"rotation": [4.99527, 0.21782, -2.4905]
				},
				"body": {
					"position": [0, -3, 0]
				},
				"foot_left_pivot": {
					"rotation": [-15, 0, 0]
				}
			}
		},
		"animation.regigigas.kneeling": {
			"loop": true,
			"bones": {
				"body": {
					"position": [0, -16, 0]
				},
				"torso": {
					"rotation": [12.42549, -5.977, -0.16468]
				},
				"chest": {
					"rotation": [7.5, 0, 0]
				},
				"shoulder_left": {
					"rotation": [0, 5, 0]
				},
				"arm_left": {
					"rotation": [27.5, 0, 0]
				},
				"arm_left_rotation": {
					"rotation": [0, 0, 50]
				},
				"arm_left2": {
					"rotation": [0, 42.5, 0]
				},
				"hand_left": {
					"rotation": [1.75378, 9.84655, 10.15108]
				},
				"finger1_left": {
					"rotation": [0, 0, -32.5]
				},
				"finger1_left2": {
					"rotation": [0, 0, 45]
				},
				"finger2_left": {
					"rotation": [39.70042, 26.11218, 20.07273]
				},
				"finger2_left2": {
					"rotation": [0, -62.5, 0]
				},
				"finger3_left": {
					"rotation": [-33.69007, -25.65891, 16.10211]
				},
				"finger3_left2": {
					"rotation": [0, 35, 0]
				},
				"shoulder_right": {
					"rotation": [0, -7.5, 0]
				},
				"arm_right": {
					"rotation": [-52.5, 0, 0]
				},
				"arm_right_rotation": {
					"rotation": [0, 0, -45]
				},
				"arm_right2": {
					"rotation": [7.5, 0, -35]
				},
				"hand_right": {
					"rotation": [0, 0, -10]
				},
				"finger1_right": {
					"rotation": [0, 0, 20]
				},
				"finger1_right2": {
					"rotation": [0, 0, -45]
				},
				"finger2_right": {
					"rotation": [31.97111, -12.4222, -1.17801]
				},
				"finger2_right2": {
					"rotation": [0, 20, 0]
				},
				"finger3_right": {
					"rotation": [-42.93246, 7.64427, -6.46635]
				},
				"finger3_right2": {
					"rotation": [0, -65, 0]
				},
				"legs": {
					"rotation": [0, -22.5, 0]
				},
				"leg_left": {
					"rotation": [25.92316, 14.44189, 3.7865]
				},
				"leg_left2": {
					"rotation": [60.77911, 2.3207, 4.37589]
				},
				"foot_left_pivot": {
					"rotation": [-7.5, 0, 0]
				},
				"leg_right": {
					"rotation": [-60.1167, 17.10379, -0.24793]
				},
				"leg_right2": {
					"rotation": [50.01629, 1.90853, -1.14465]
				},
				"foot_right": {
					"rotation": [12.5, 0, 0]
				},
				"foot_right_pivot": {
					"rotation": [0, 0, -7.5]
				}
			}
		}
	}
}